[
    {
        "load": 56.52,
        "cpu_time": 75008
    },
    {
        "id": "http://192.168.0.173:8081/1-7.html",
        "objs": [
            {
                "activityId": "Networking_0",
                "id": "4380EA5683E1C396A3470C94D53B136D",
                "startTime": 0.0,
                "endTime": 22.972,
                "mimeType": "text/html",
                "url": "http://192.168.0.173:8081/1-7.html",
                "fromScript": "Null",
                "transferSize": 93,
                "responseReceivedTime": 3.422,
                "statusCode": 200
            },
            {
                "activityId": "Loading_0",
                "fromScript": null,
                "styleSheetUrl": null,
                "url": "http://192.168.0.173:8081/1-7.html",
                "name": "ParseHTML",
                "startTime": 25.229,
                "endTime": 28.295
            },
            {
                "activityId": "Loading_1",
                "fromScript": null,
                "styleSheetUrl": null,
                "url": "http://192.168.0.173:8081/1-7.html",
                "name": "ParseHTML",
                "startTime": 54.97,
                "endTime": 59.744
            }
        ]
    },
    {
        "id": "http://192.168.0.173:8081/1-7.js",
        "objs": [
            {
                "activityId": "Networking_1",
                "id": "1000026083.5619",
                "startTime": 25.816,
                "endTime": 48.415,
                "mimeType": "application/javascript",
                "url": "http://192.168.0.173:8081/1-7.js",
                "fromScript": "Null",
                "transferSize": 73,
                "responseReceivedTime": 42.321,
                "statusCode": 200
            },
            {
                "activityId": "Scripting_0",
                "url": "http://192.168.0.173:8081/1-7.js",
                "startTime": 48.721,
                "endTime": 54.779
            }
        ]
    },
    {
        "id": "Rendering",
        "objs": [
            {
                "activityId": "Rendering_1",
                "startTime": 2.136,
                "name": "UpdateLayerTree",
                "endTime": 2.214
            },
            {
                "activityId": "Rendering_2",
                "startTime": 56.603,
                "name": "Layout",
                "endTime": 57.098
            },
            {
                "activityId": "Rendering_3",
                "startTime": 68.177,
                "name": "UpdateLayerTree",
                "endTime": 68.846
            }
        ]
    },
    {
        "id": "Painting",
        "objs": [
            {
                "activityId": "Painting_1",
                "startTime": 2.384,
                "name": "CompositeLayers",
                "endTime": 2.958,
                "layerTreeId": 1
            },
            {
                "activityId": "Painting_2",
                "startTime": 68.937,
                "name": "Paint",
                "endTime": 69.079
            },
            {
                "activityId": "Painting_3",
                "startTime": 74.417,
                "name": "CompositeLayers",
                "endTime": 75.008,
                "layerTreeId": 1
            }
        ]
    },
    {
        "id": "Deps",
        "objs": [
            {
                "time": -1,
                "a1": "Networking_0",
                "a2": "Loading_0"
            },
            {
                "time": 25.816,
                "a1": "Loading_0",
                "a2": "Networking_1"
            },
            {
                "time": -1,
                "a1": "Networking_1",
                "a2": "Scripting_0"
            },
            {
                "time": -1,
                "a1": "Networking_0",
                "a2": "Loading_1"
            },
            {
                "time": -1,
                "a1": "Scripting_0",
                "a2": "Loading_1"
            },
            {
                "time": -1,
                "a1": "Loading_0",
                "a2": "Loading_1"
            }
        ]
    },
    {
        "id": "Netlog",
        "dns": {},
        "sockets": {
            "0x80e5": {
                "bytes_in": 281,
                "bytes_out": 432
            },
            "0x80e9": {
                "bytes_in": 274,
                "bytes_out": 363
            }
        },
        "dnsTime": -1,
        "sockets_bytes_in": 555,
        "sockets_bytes_out": 795,
        "ssl_sockets_bytes_out": 0,
        "ssl_sockets_bytes_in": 0
    },
    {
        "criticalPath": [
            "Networking_0",
            "Loading_0",
            "Networking_1",
            "Scripting_0",
            "Loading_1"
        ],
        "networkingTime": 22.6,
        "computationTime": 34.39
    }
]