[
    {
        "load": 60.68,
        "cpu_time": 91924
    },
    {
        "id": "http://192.168.0.173:8081/1-7.html",
        "objs": [
            {
                "activityId": "Networking_0",
                "id": "EA2A01E60B558191BD8E447E251D371D",
                "startTime": 0.0,
                "endTime": 29.825,
                "mimeType": "text/html",
                "url": "http://192.168.0.173:8081/1-7.html",
                "fromScript": "Null",
                "transferSize": 93,
                "responseReceivedTime": 4.118,
                "statusCode": 200
            },
            {
                "activityId": "Loading_0",
                "fromScript": null,
                "styleSheetUrl": null,
                "url": "http://192.168.0.173:8081/1-7.html",
                "name": "ParseHTML",
                "startTime": 32.547,
                "endTime": 36.313
            },
            {
                "activityId": "Loading_1",
                "fromScript": null,
                "styleSheetUrl": null,
                "url": "http://192.168.0.173:8081/1-7.html",
                "name": "ParseHTML",
                "startTime": 59.091,
                "endTime": 62.544
            }
        ]
    },
    {
        "id": "http://192.168.0.173:8081/1-7.js",
        "objs": [
            {
                "activityId": "Networking_1",
                "id": "1000026083.4689",
                "startTime": 33.13,
                "endTime": 54.178,
                "mimeType": "application/javascript",
                "url": "http://192.168.0.173:8081/1-7.js",
                "fromScript": "Null",
                "transferSize": 164,
                "responseReceivedTime": 49.975,
                "statusCode": 200
            },
            {
                "activityId": "Scripting_0",
                "url": "http://192.168.0.173:8081/1-7.js",
                "startTime": 54.633,
                "endTime": 58.875
            }
        ]
    },
    {
        "id": "Rendering",
        "objs": [
            {
                "activityId": "Rendering_1",
                "startTime": 60.817,
                "name": "Layout",
                "endTime": 61.36
            },
            {
                "activityId": "Rendering_2",
                "startTime": 86.628,
                "name": "UpdateLayerTree",
                "endTime": 87.271
            }
        ]
    },
    {
        "id": "Painting",
        "objs": [
            {
                "activityId": "Painting_1",
                "startTime": 87.364,
                "name": "Paint",
                "endTime": 87.53
            },
            {
                "activityId": "Painting_2",
                "startTime": 91.392,
                "name": "CompositeLayers",
                "endTime": 91.924,
                "layerTreeId": 1
            }
        ]
    },
    {
        "id": "Deps",
        "objs": [
            {
                "time": -1,
                "a1": "Networking_0",
                "a2": "Loading_0"
            },
            {
                "time": 33.13,
                "a1": "Loading_0",
                "a2": "Networking_1"
            },
            {
                "time": -1,
                "a1": "Networking_1",
                "a2": "Scripting_0"
            },
            {
                "time": -1,
                "a1": "Networking_0",
                "a2": "Loading_1"
            },
            {
                "time": -1,
                "a1": "Scripting_0",
                "a2": "Loading_1"
            },
            {
                "time": -1,
                "a1": "Loading_0",
                "a2": "Loading_1"
            }
        ]
    },
    {
        "id": "Netlog",
        "dns": {},
        "sockets": {
            "0x6ac3": {
                "bytes_in": 0,
                "bytes_out": 0
            },
            "0x6ad0": {
                "bytes_in": 281,
                "bytes_out": 432
            },
            "0x6ad2": {
                "bytes_in": 366,
                "bytes_out": 363
            }
        },
        "dnsTime": -1,
        "sockets_bytes_in": 647,
        "sockets_bytes_out": 795,
        "ssl_sockets_bytes_out": 0,
        "ssl_sockets_bytes_in": 0
    },
    {
        "criticalPath": [
            "Networking_0",
            "Loading_0",
            "Networking_1",
            "Scripting_0",
            "Loading_1"
        ],
        "networkingTime": 21.05,
        "computationTime": 38.1
    }
]