[
    {
        "load": 57.77,
        "cpu_time": 73615
    },
    {
        "id": "http://192.168.0.173:8081/1-5.html",
        "objs": [
            {
                "activityId": "Networking_0",
                "id": "E9695076E35FA43DE6446B455236407F",
                "startTime": 0.0,
                "endTime": 21.614,
                "mimeType": "text/html",
                "url": "http://192.168.0.173:8081/1-5.html",
                "fromScript": "Null",
                "transferSize": 93,
                "responseReceivedTime": 2.58,
                "statusCode": 200
            },
            {
                "activityId": "Loading_0",
                "fromScript": null,
                "styleSheetUrl": null,
                "url": "http://192.168.0.173:8081/1-5.html",
                "name": "ParseHTML",
                "startTime": 23.594,
                "endTime": 25.873
            },
            {
                "activityId": "Loading_1",
                "fromScript": null,
                "styleSheetUrl": null,
                "url": "http://192.168.0.173:8081/1-5.html",
                "name": "ParseHTML",
                "startTime": 55.656,
                "endTime": 59.493
            }
        ]
    },
    {
        "id": "http://192.168.0.173:8081/1-5.js",
        "objs": [
            {
                "activityId": "Networking_1",
                "id": "1000026083.1620",
                "startTime": 24.22,
                "endTime": 41.263,
                "mimeType": "application/javascript",
                "url": "http://192.168.0.173:8081/1-5.js",
                "fromScript": "Null",
                "transferSize": 65,
                "responseReceivedTime": 38.509,
                "statusCode": 200
            },
            {
                "activityId": "Scripting_0",
                "url": "http://192.168.0.173:8081/1-5.js",
                "startTime": 41.597,
                "endTime": 55.464
            }
        ]
    },
    {
        "id": "Rendering",
        "objs": [
            {
                "activityId": "Rendering_1",
                "startTime": 57.885,
                "name": "Layout",
                "endTime": 58.434
            },
            {
                "activityId": "Rendering_2",
                "startTime": 66.158,
                "name": "UpdateLayerTree",
                "endTime": 66.991
            }
        ]
    },
    {
        "id": "Painting",
        "objs": [
            {
                "activityId": "Painting_1",
                "startTime": 67.087,
                "name": "Paint",
                "endTime": 67.26
            },
            {
                "activityId": "Painting_2",
                "startTime": 72.908,
                "name": "CompositeLayers",
                "endTime": 73.615,
                "layerTreeId": 1
            }
        ]
    },
    {
        "id": "Deps",
        "objs": [
            {
                "time": -1,
                "a1": "Networking_0",
                "a2": "Loading_0"
            },
            {
                "time": 24.22,
                "a1": "Loading_0",
                "a2": "Networking_1"
            },
            {
                "time": -1,
                "a1": "Networking_1",
                "a2": "Scripting_0"
            },
            {
                "time": -1,
                "a1": "Networking_0",
                "a2": "Loading_1"
            },
            {
                "time": -1,
                "a1": "Scripting_0",
                "a2": "Loading_1"
            },
            {
                "time": -1,
                "a1": "Loading_0",
                "a2": "Loading_1"
            }
        ]
    },
    {
        "id": "Netlog",
        "dns": {},
        "sockets": {
            "0x2510": {
                "bytes_in": 281,
                "bytes_out": 432
            },
            "0x2514": {
                "bytes_in": 266,
                "bytes_out": 363
            }
        },
        "dnsTime": -1,
        "sockets_bytes_in": 547,
        "sockets_bytes_out": 795,
        "ssl_sockets_bytes_out": 0,
        "ssl_sockets_bytes_in": 0
    },
    {
        "criticalPath": [
            "Networking_0",
            "Loading_0",
            "Networking_1",
            "Scripting_0",
            "Loading_1"
        ],
        "networkingTime": 17.04,
        "computationTime": 39.94
    }
]