[
    {
        "load": 109.58,
        "cpu_time": 126069
    },
    {
        "id": "http://192.168.0.173:8081/1-7.html",
        "objs": [
            {
                "activityId": "Networking_0",
                "id": "54E30531CD9E27E366EF379E1ECF3BF1",
                "startTime": 0.0,
                "endTime": 24.29,
                "mimeType": "text/html",
                "url": "http://192.168.0.173:8081/1-7.html",
                "fromScript": "Null",
                "transferSize": 93,
                "responseReceivedTime": 2.314,
                "statusCode": 200
            },
            {
                "activityId": "Loading_0",
                "fromScript": null,
                "styleSheetUrl": null,
                "url": "http://192.168.0.173:8081/1-7.html",
                "name": "ParseHTML",
                "startTime": 26.281,
                "endTime": 28.64
            },
            {
                "activityId": "Loading_1",
                "fromScript": null,
                "styleSheetUrl": null,
                "url": "http://192.168.0.173:8081/1-7.html",
                "name": "ParseHTML",
                "startTime": 108.248,
                "endTime": 111.05
            }
        ]
    },
    {
        "id": "http://192.168.0.173:8081/1-7.js",
        "objs": [
            {
                "activityId": "Networking_1",
                "id": "1000026083.1863",
                "startTime": 26.807,
                "endTime": 48.67,
                "mimeType": "application/javascript",
                "url": "http://192.168.0.173:8081/1-7.js",
                "fromScript": "Null",
                "transferSize": 65,
                "responseReceivedTime": 43.046,
                "statusCode": 200
            },
            {
                "activityId": "Scripting_0",
                "url": "http://192.168.0.173:8081/1-7.js",
                "startTime": 48.987,
                "endTime": 108.063
            }
        ]
    },
    {
        "id": "Rendering",
        "objs": [
            {
                "activityId": "Rendering_1",
                "startTime": 109.669,
                "name": "Layout",
                "endTime": 110.121
            },
            {
                "activityId": "Rendering_2",
                "startTime": 113.553,
                "name": "UpdateLayerTree",
                "endTime": 114.413
            },
            {
                "activityId": "Rendering_3",
                "startTime": 125.847,
                "name": "UpdateLayerTree",
                "endTime": 125.92599999999999
            }
        ]
    },
    {
        "id": "Painting",
        "objs": [
            {
                "activityId": "Painting_1",
                "startTime": 114.531,
                "name": "Paint",
                "endTime": 114.74000000000001
            },
            {
                "activityId": "Painting_2",
                "startTime": 120.695,
                "name": "CompositeLayers",
                "endTime": 121.271,
                "layerTreeId": 1
            },
            {
                "activityId": "Painting_3",
                "startTime": 125.974,
                "name": "CompositeLayers",
                "endTime": 126.069,
                "layerTreeId": 1
            }
        ]
    },
    {
        "id": "Deps",
        "objs": [
            {
                "time": -1,
                "a1": "Networking_0",
                "a2": "Loading_0"
            },
            {
                "time": 26.807,
                "a1": "Loading_0",
                "a2": "Networking_1"
            },
            {
                "time": -1,
                "a1": "Networking_1",
                "a2": "Scripting_0"
            },
            {
                "time": -1,
                "a1": "Networking_0",
                "a2": "Loading_1"
            },
            {
                "time": -1,
                "a1": "Scripting_0",
                "a2": "Loading_1"
            },
            {
                "time": -1,
                "a1": "Loading_0",
                "a2": "Loading_1"
            }
        ]
    },
    {
        "id": "Netlog",
        "dns": {},
        "sockets": {
            "0x2a8d": {
                "bytes_in": 281,
                "bytes_out": 432
            },
            "0x2a8f": {
                "bytes_in": 266,
                "bytes_out": 363
            }
        },
        "dnsTime": -1,
        "sockets_bytes_in": 547,
        "sockets_bytes_out": 795,
        "ssl_sockets_bytes_out": 0,
        "ssl_sockets_bytes_in": 0
    },
    {
        "criticalPath": [
            "Networking_0",
            "Loading_0",
            "Networking_1",
            "Scripting_0",
            "Loading_1"
        ],
        "networkingTime": 21.86,
        "computationTime": 86.69
    }
]