[
    {
        "load": 46.91,
        "cpu_time": 76768
    },
    {
        "id": "http://192.168.0.173:8081/1-6.html",
        "objs": [
            {
                "activityId": "Networking_0",
                "id": "FA9603975C82C86BB1E215E827188146",
                "startTime": 0.0,
                "endTime": 21.255,
                "mimeType": "text/html",
                "url": "http://192.168.0.173:8081/1-6.html",
                "fromScript": "Null",
                "transferSize": 93,
                "responseReceivedTime": 3.268,
                "statusCode": 200
            },
            {
                "activityId": "Loading_0",
                "fromScript": null,
                "styleSheetUrl": null,
                "url": "http://192.168.0.173:8081/1-6.html",
                "name": "ParseHTML",
                "startTime": 23.785,
                "endTime": 25.994
            },
            {
                "activityId": "Loading_1",
                "fromScript": null,
                "styleSheetUrl": null,
                "url": "http://192.168.0.173:8081/1-6.html",
                "name": "ParseHTML",
                "startTime": 45.041,
                "endTime": 48.68
            }
        ]
    },
    {
        "id": "http://192.168.0.173:8081/1-6.js",
        "objs": [
            {
                "activityId": "Networking_1",
                "id": "1000026083.4596",
                "startTime": 24.313,
                "endTime": 42.279,
                "mimeType": "application/javascript",
                "url": "http://192.168.0.173:8081/1-6.js",
                "fromScript": "Null",
                "transferSize": 164,
                "responseReceivedTime": 38.573,
                "statusCode": 200
            },
            {
                "activityId": "Scripting_0",
                "url": "http://192.168.0.173:8081/1-6.js",
                "startTime": 42.632,
                "endTime": 44.82
            }
        ]
    },
    {
        "id": "Rendering",
        "objs": [
            {
                "activityId": "Rendering_1",
                "startTime": 47.032,
                "name": "Layout",
                "endTime": 47.627
            },
            {
                "activityId": "Rendering_2",
                "startTime": 63.363,
                "name": "UpdateLayerTree",
                "endTime": 64.533
            },
            {
                "activityId": "Rendering_3",
                "startTime": 76.147,
                "name": "UpdateLayerTree",
                "endTime": 76.549
            }
        ]
    },
    {
        "id": "Painting",
        "objs": [
            {
                "activityId": "Painting_1",
                "startTime": 64.628,
                "name": "Paint",
                "endTime": 64.776
            },
            {
                "activityId": "Painting_2",
                "startTime": 69.647,
                "name": "CompositeLayers",
                "endTime": 70.152,
                "layerTreeId": 1
            },
            {
                "activityId": "Painting_3",
                "startTime": 76.607,
                "name": "CompositeLayers",
                "endTime": 76.768,
                "layerTreeId": 1
            }
        ]
    },
    {
        "id": "Deps",
        "objs": [
            {
                "time": -1,
                "a1": "Networking_0",
                "a2": "Loading_0"
            },
            {
                "time": 24.313,
                "a1": "Loading_0",
                "a2": "Networking_1"
            },
            {
                "time": -1,
                "a1": "Networking_1",
                "a2": "Scripting_0"
            },
            {
                "time": -1,
                "a1": "Networking_0",
                "a2": "Loading_1"
            },
            {
                "time": -1,
                "a1": "Scripting_0",
                "a2": "Loading_1"
            },
            {
                "time": -1,
                "a1": "Loading_0",
                "a2": "Loading_1"
            }
        ]
    },
    {
        "id": "Netlog",
        "dns": {},
        "sockets": {
            "0x68bd": {
                "bytes_in": 281,
                "bytes_out": 432
            },
            "0x68bf": {
                "bytes_in": 366,
                "bytes_out": 363
            }
        },
        "dnsTime": -1,
        "sockets_bytes_in": 647,
        "sockets_bytes_out": 795,
        "ssl_sockets_bytes_out": 0,
        "ssl_sockets_bytes_in": 0
    },
    {
        "criticalPath": [
            "Networking_0",
            "Loading_0",
            "Networking_1",
            "Scripting_0",
            "Loading_1"
        ],
        "networkingTime": 17.97,
        "computationTime": 27.61
    }
]