[
    {
        "load": 59.55,
        "cpu_time": 89138
    },
    {
        "id": "http://192.168.0.173:8081/1-2.html",
        "objs": [
            {
                "activityId": "Networking_0",
                "id": "B98ED41D56FD7D114FA630C765B5A94D",
                "startTime": 0.0,
                "endTime": 33.171,
                "mimeType": "text/html",
                "url": "http://192.168.0.173:8081/1-2.html",
                "fromScript": "Null",
                "transferSize": 93,
                "responseReceivedTime": 5.035,
                "statusCode": 200
            },
            {
                "activityId": "Loading_0",
                "fromScript": null,
                "styleSheetUrl": null,
                "url": "http://192.168.0.173:8081/1-2.html",
                "name": "ParseHTML",
                "startTime": 36.95,
                "endTime": 39.196
            },
            {
                "activityId": "Loading_1",
                "fromScript": null,
                "styleSheetUrl": null,
                "url": "http://192.168.0.173:8081/1-2.html",
                "name": "ParseHTML",
                "startTime": 57.962,
                "endTime": 61.233
            }
        ]
    },
    {
        "id": "http://192.168.0.173:8081/1-2.js",
        "objs": [
            {
                "activityId": "Networking_1",
                "id": "1000026083.2109",
                "startTime": 37.521,
                "endTime": 56.786,
                "mimeType": "application/javascript",
                "url": "http://192.168.0.173:8081/1-2.js",
                "fromScript": "Null",
                "transferSize": 73,
                "responseReceivedTime": 55.777,
                "statusCode": 200
            },
            {
                "activityId": "Scripting_0",
                "url": "http://192.168.0.173:8081/1-2.js",
                "startTime": 57.087,
                "endTime": 57.772
            }
        ]
    },
    {
        "id": "Rendering",
        "objs": [
            {
                "activityId": "Rendering_1",
                "startTime": 59.659,
                "name": "Layout",
                "endTime": 60.183
            },
            {
                "activityId": "Rendering_2",
                "startTime": 82.576,
                "name": "UpdateLayerTree",
                "endTime": 83.20599999999999
            }
        ]
    },
    {
        "id": "Painting",
        "objs": [
            {
                "activityId": "Painting_1",
                "startTime": 83.292,
                "name": "Paint",
                "endTime": 83.46300000000001
            },
            {
                "activityId": "Painting_2",
                "startTime": 88.518,
                "name": "CompositeLayers",
                "endTime": 89.138,
                "layerTreeId": 1
            }
        ]
    },
    {
        "id": "Deps",
        "objs": [
            {
                "time": -1,
                "a1": "Networking_0",
                "a2": "Loading_0"
            },
            {
                "time": 37.521,
                "a1": "Loading_0",
                "a2": "Networking_1"
            },
            {
                "time": -1,
                "a1": "Networking_1",
                "a2": "Scripting_0"
            },
            {
                "time": -1,
                "a1": "Networking_0",
                "a2": "Loading_1"
            },
            {
                "time": -1,
                "a1": "Scripting_0",
                "a2": "Loading_1"
            },
            {
                "time": -1,
                "a1": "Loading_0",
                "a2": "Loading_1"
            }
        ]
    },
    {
        "id": "Netlog",
        "dns": {},
        "sockets": {
            "0x3009": {
                "bytes_in": 281,
                "bytes_out": 432
            },
            "0x300b": {
                "bytes_in": 274,
                "bytes_out": 363
            },
            "0x300f": {
                "bytes_in": 0,
                "bytes_out": 0
            }
        },
        "dnsTime": -1,
        "sockets_bytes_in": 555,
        "sockets_bytes_out": 795,
        "ssl_sockets_bytes_out": 0,
        "ssl_sockets_bytes_in": 0
    },
    {
        "criticalPath": [
            "Networking_0",
            "Loading_0",
            "Networking_1",
            "Scripting_0",
            "Loading_1"
        ],
        "networkingTime": 19.27,
        "computationTime": 37.7
    }
]